gluegun/__init__.py
gluegun/gluegun.py
gluegun-1.0.6.dist-info/LICENSE
gluegun-1.0.6.dist-info/METADATA
gluegun-1.0.6.dist-info/WHEEL
gluegun-1.0.6.dist-info/top_level.txt
gluegun-1.0.6.dist-info/RECORD
