Metadata-Version: 2.1
Name: gluegun
Version: 1.0.6
Summary: ETL utility functions built on Pandas
Home-page: https://github.com/hotgluexyz/gluegun
Author: hotglue
Author-email: hello@hotglue.xyz
License: MIT
Platform: UNKNOWN
Requires-Dist: xlrd (==1.2.0)
Requires-Dist: numpy (>=1.14.3)
Requires-Dist: pandas (>=0.23.0)
